ngio/__init__.py
ngio/common/__init__.py
ngio/common/_dimensions.py
ngio/common/_masking_roi.py
ngio/common/_pyramid.py
ngio/common/_roi.py
ngio/common/_synt_images_utils.py
ngio/common/_zoom.py
ngio/experimental/__init__.py
ngio/experimental/iterators/__init__.py
ngio/experimental/iterators/_abstract_iterator.py
ngio/experimental/iterators/_feature.py
ngio/experimental/iterators/_image_processing.py
ngio/experimental/iterators/_mappers.py
ngio/experimental/iterators/_rois_utils.py
ngio/experimental/iterators/_segmentation.py
ngio/hcs/__init__.py
ngio/hcs/_plate.py
ngio/images/__init__.py
ngio/images/_abstract_image.py
ngio/images/_create.py
ngio/images/_create_synt_container.py
ngio/images/_image.py
ngio/images/_label.py
ngio/images/_masked_image.py
ngio/images/_ome_zarr_container.py
ngio/images/_table_ops.py
ngio/io_pipes/__init__.py
ngio/io_pipes/_io_pipes.py
ngio/io_pipes/_io_pipes_masked.py
ngio/io_pipes/_io_pipes_roi.py
ngio/io_pipes/_io_pipes_types.py
ngio/io_pipes/_match_shape.py
ngio/io_pipes/_ops_axes.py
ngio/io_pipes/_ops_slices.py
ngio/io_pipes/_ops_slices_utils.py
ngio/io_pipes/_ops_transforms.py
ngio/io_pipes/_zoom_transform.py
ngio/ome_zarr_meta/__init__.py
ngio/ome_zarr_meta/_meta_handlers.py
ngio/ome_zarr_meta/ngio_specs/__init__.py
ngio/ome_zarr_meta/ngio_specs/_axes.py
ngio/ome_zarr_meta/ngio_specs/_channels.py
ngio/ome_zarr_meta/ngio_specs/_dataset.py
ngio/ome_zarr_meta/ngio_specs/_ngio_hcs.py
ngio/ome_zarr_meta/ngio_specs/_ngio_image.py
ngio/ome_zarr_meta/ngio_specs/_pixel_size.py
ngio/ome_zarr_meta/v04/__init__.py
ngio/ome_zarr_meta/v04/_custom_models.py
ngio/ome_zarr_meta/v04/_v04_spec_utils.py
ngio/resources/__init__.py
ngio/resources/resource_model.py
ngio/resources/20200812-CardiomyocyteDifferentiation14-Cycle1_B03/mask.png
ngio/resources/20200812-CardiomyocyteDifferentiation14-Cycle1_B03/nuclei.png
ngio/resources/20200812-CardiomyocyteDifferentiation14-Cycle1_B03/raw.jpg
ngio/tables/__init__.py
ngio/tables/_abstract_table.py
ngio-0.4.7.dist-info/METADATA
ngio-0.4.7.dist-info/WHEEL
ngio-0.4.7.dist-info/licenses/LICENSE
ngio-0.4.7.dist-info/RECORD
