Metadata-Version: 2.4
Name: ngio
Version: 0.4.7
Summary: Next Generation file format IO
Project-URL: homepage, https://github.com/BioVisionCenter/ngio
Project-URL: repository, https://github.com/BioVisionCenter/ngio
Author-email: Lorenzo Cerrone <lorenzo.cerrone@uzh.ch>
License: BSD-3-Clause
License-File: LICENSE
Classifier: Development Status :: 3 - Alpha
Classifier: License :: OSI Approved :: BSD License
Classifier: Programming Language :: Python :: 3
Classifier: Programming Language :: Python :: 3.11
Classifier: Programming Language :: Python :: 3.12
Classifier: Programming Language :: Python :: 3.13
Classifier: Typing :: Typed
Requires-Python: <3.14,>=3.11
Requires-Dist: aiohttp
Requires-Dist: anndata<0.11.4,>=0.8.0
Requires-Dist: dask[array]<2025.11.0
Requires-Dist: dask[distributed]<2025.11.0
Requires-Dist: filelock
Requires-Dist: numpy
Requires-Dist: ome-zarr-models
Requires-Dist: pandas>=1.2.0
Requires-Dist: pillow
Requires-Dist: polars
Requires-Dist: pooch
Requires-Dist: pyarrow
Requires-Dist: pydantic
Requires-Dist: requests
Requires-Dist: zarr<3
Provides-Extra: dev
Requires-Dist: devtools; extra == 'dev'
Requires-Dist: matplotlib; extra == 'dev'
Requires-Dist: mypy; extra == 'dev'
Requires-Dist: napari; extra == 'dev'
Requires-Dist: notebook; extra == 'dev'
Requires-Dist: pdbpp; extra == 'dev'
Requires-Dist: pre-commit; extra == 'dev'
Requires-Dist: pympler; extra == 'dev'
Requires-Dist: pyqt5; extra == 'dev'
Requires-Dist: rich; extra == 'dev'
Requires-Dist: ruff; extra == 'dev'
Requires-Dist: scikit-image; extra == 'dev'
Provides-Extra: docs
Requires-Dist: griffe-typingdoc; extra == 'docs'
Requires-Dist: markdown-exec[ansi]; extra == 'docs'
Requires-Dist: matplotlib; extra == 'docs'
Requires-Dist: mike; extra == 'docs'
Requires-Dist: mkdocs; extra == 'docs'
Requires-Dist: mkdocs-autorefs; extra == 'docs'
Requires-Dist: mkdocs-git-committers-plugin-2; extra == 'docs'
Requires-Dist: mkdocs-git-revision-date-localized-plugin; extra == 'docs'
Requires-Dist: mkdocs-include-markdown-plugin; extra == 'docs'
Requires-Dist: mkdocs-jupyter; extra == 'docs'
Requires-Dist: mkdocs-material; extra == 'docs'
Requires-Dist: mkdocstrings[python]; extra == 'docs'
Requires-Dist: rich; extra == 'docs'
Requires-Dist: scikit-image; extra == 'docs'
Requires-Dist: tabulate; extra == 'docs'
Provides-Extra: test
Requires-Dist: pytest; extra == 'test'
Requires-Dist: pytest-cov; extra == 'test'
Requires-Dist: scikit-image; extra == 'test'
